Scrapset/Scrapset.py
Scrapset/__init__.py
Scrapset-1.4.0.dist-info/METADATA
Scrapset-1.4.0.dist-info/WHEEL
Scrapset-1.4.0.dist-info/licence.txt
Scrapset-1.4.0.dist-info/top_level.txt
Scrapset-1.4.0.dist-info/RECORD
