Metadata-Version: 2.1
Name: Scrapset
Version: 1.4.0
Summary: DataScraper: Effortless Dataset Extraction
Author: Ibrahim
Author-email: string2025@gmail.com
License-File: licence.txt
Requires-Dist: selenium
